strsplitter/__init__.py
strsplitter/__main__.py
strsplitter/iterator.py
strsplitter/py.typed
strsplitter/splitter.py
strsplitter/strsplitter.py
strsplitter-1.0.3.dist-info/licenses/LICENSE.txt
strsplitter-1.0.3.dist-info/METADATA
strsplitter-1.0.3.dist-info/WHEEL
strsplitter-1.0.3.dist-info/entry_points.txt
strsplitter-1.0.3.dist-info/top_level.txt
strsplitter-1.0.3.dist-info/RECORD
