Metadata-Version: 2.4
Name: strsplitter
Version: 1.0.3
Summary: A string splitting utility with customizable splitters and filtering.
Author-email: Kessoum Khaled <khaled.kessoum@univ-bejaia.dz>
Project-URL: Homepage, https://github.com/ckalandk/strsplit
Project-URL: Issues, https://github.com/ckalandk/strsplit/issues
Keywords: string,split,utility,filtering
Classifier: Programming Language :: Python :: 3
Classifier: Programming Language :: Python :: 3.10
Classifier: Programming Language :: Python :: 3.11
Classifier: Programming Language :: Python :: 3.12
Classifier: Programming Language :: Python :: 3.13
Classifier: License :: OSI Approved :: MIT License
Classifier: Operating System :: OS Independent
Requires-Python: >=3.10
License-File: LICENSE.txt
Requires-Dist: click>=8.2.1
Dynamic: license-file
